ofxclient/__init__.py
ofxclient/fi_data.json
ofxclient/ofxclient-cli.py
ofxclient/ofxclient.py
ofxclient/ofxclient.pyc
ofxclient/ofxparser.py
ofxclient/ofxtemplates.py
ofxclient/__pycache__/__init__.cpython-35.pyc
ofxclient/__pycache__/ofxclient-cli.cpython-35.pyc
ofxclient/__pycache__/ofxclient.cpython-35.pyc
ofxclient/__pycache__/ofxparser.cpython-35.pyc
ofxclient/__pycache__/ofxtemplates.cpython-35.pyc
ofxclient_python-0.0.8.dist-info/DESCRIPTION.rst
ofxclient_python-0.0.8.dist-info/METADATA
ofxclient_python-0.0.8.dist-info/RECORD
ofxclient_python-0.0.8.dist-info/WHEEL
ofxclient_python-0.0.8.dist-info/metadata.json
ofxclient_python-0.0.8.dist-info/top_level.txt
