Metadata-Version: 2.0
Name: ofxclient-python
Version: 0.0.8
Summary: Open Financial Data Exchange (OFX) client API and command-line interface
Home-page: https://github.com/denvaar/ofxclient-python
Author: Denver Smith
Author-email: denverpsmith@gmail.com
License: MIT License
Platform: UNKNOWN
Classifier: Intended Audience :: Developers
Classifier: License :: OSI Approved :: MIT License
Classifier: Operating System :: OS Independent
Classifier: Programming Language :: Python
Classifier: Programming Language :: Python :: 3
Classifier: Programming Language :: Python :: 3.4
Classifier: Programming Language :: Python :: 3.5
Classifier: Topic :: Internet :: WWW/HTTP
